wagtail_embed_videos/__init__.py
wagtail_embed_videos/admin.py
wagtail_embed_videos/admin_urls.py
wagtail_embed_videos/apps.py
wagtail_embed_videos/blocks.py
wagtail_embed_videos/edit_handlers.py
wagtail_embed_videos/forms.py
wagtail_embed_videos/models.py
wagtail_embed_videos/permissions.py
wagtail_embed_videos/wagtail_hooks.py
wagtail_embed_videos/widgets.py
wagtail_embed_videos/locale/pt_BR/LC_MESSAGES/django.mo
wagtail_embed_videos/locale/pt_BR/LC_MESSAGES/django.po
wagtail_embed_videos/locale/ru/LC_MESSAGES/django.mo
wagtail_embed_videos/locale/ru/LC_MESSAGES/django.po
wagtail_embed_videos/migrations/0001_initial.py
wagtail_embed_videos/migrations/0002_auto_20180822_0945.py
wagtail_embed_videos/migrations/0003_embedvideo_collection.py
wagtail_embed_videos/migrations/0004_auto_20211103_0746.py
wagtail_embed_videos/migrations/0005_auto_20211103_0802.py
wagtail_embed_videos/migrations/0006_auto_20211104_0557.py
wagtail_embed_videos/migrations/0007_auto_20211109_0511.py
wagtail_embed_videos/migrations/__init__.py
wagtail_embed_videos/static/wagtail_embed_videos/css/embed-video-chooser.css
wagtail_embed_videos/static/wagtail_embed_videos/js/embed-video-chooser-modal.js
wagtail_embed_videos/static/wagtail_embed_videos/js/embed-video-chooser.js
wagtail_embed_videos/templates/wagtail_embed_videos/bulk_actions/confirm_bulk_add_tags.html
wagtail_embed_videos/templates/wagtail_embed_videos/bulk_actions/confirm_bulk_add_to_collection.html
wagtail_embed_videos/templates/wagtail_embed_videos/bulk_actions/confirm_bulk_delete.html
wagtail_embed_videos/templates/wagtail_embed_videos/bulk_actions/list_items_with_no_access.html
wagtail_embed_videos/templates/wagtail_embed_videos/chooser/chooser.html
wagtail_embed_videos/templates/wagtail_embed_videos/chooser/results.html
wagtail_embed_videos/templates/wagtail_embed_videos/chooser/upload_form.html
wagtail_embed_videos/templates/wagtail_embed_videos/edit_handlers/embed_video_chooser_panel.html
wagtail_embedvideos-0.5.12.dist-info/AUTHORS.rst
wagtail_embedvideos-0.5.12.dist-info/LICENSE
wagtail_embedvideos-0.5.12.dist-info/METADATA
wagtail_embedvideos-0.5.12.dist-info/WHEEL
wagtail_embedvideos-0.5.12.dist-info/top_level.txt
wagtail_embedvideos-0.5.12.dist-info/RECORD
