Metadata-Version: 2.1
Name: wagtail-embedvideos
Version: 0.5.12
Summary: Embed Videos for Wagtail CMS
Home-page: https://github.com/bashu/wagtail-embedvideos
Author: InfoPortugal S.A.
Author-email: suporte24@infoportugal.com
Maintainer: Basil Shubin
Maintainer-email: basil.shubin@gmail.com
License: BSD License
Download-URL: https://github.com/bashu/wagtail-embedvideos/zipball/master
Platform: UNKNOWN
Classifier: Development Status :: 5 - Production/Stable
Classifier: Environment :: Web Environment
Classifier: Intended Audience :: Developers
Classifier: License :: OSI Approved :: BSD License
Classifier: Operating System :: OS Independent
Classifier: Programming Language :: Python
Classifier: Programming Language :: Python :: 3 :: Only
Classifier: Programming Language :: Python :: 3.6
Classifier: Programming Language :: Python :: 3.7
Classifier: Programming Language :: Python :: 3.8
Classifier: Programming Language :: Python :: 3.9
Classifier: Framework :: Django
Classifier: Framework :: Django :: 2.2
Classifier: Framework :: Django :: 3.0
Classifier: Framework :: Django :: 3.1
Classifier: Framework :: Django :: 3.2
Classifier: Framework :: Wagtail
Classifier: Framework :: Wagtail :: 2
License-File: LICENSE
License-File: AUTHORS.rst
Requires-Dist: django-embed-video (>1.3)
Requires-Dist: wagtail (<3.0,>2.11)
Provides-Extra: develop
Requires-Dist: tox ; extra == 'develop'
Requires-Dist: django ; extra == 'develop'
Requires-Dist: mock-django ; extra == 'develop'
Requires-Dist: mock ; extra == 'develop'
Requires-Dist: pytest-django ; extra == 'develop'
Requires-Dist: pytest ; extra == 'develop'
Provides-Extra: test
Requires-Dist: mock-django ; extra == 'test'
Requires-Dist: mock ; extra == 'test'
Requires-Dist: pytest-django ; extra == 'test'
Requires-Dist: pytest-cov ; extra == 'test'
Requires-Dist: pytest ; extra == 'test'
